aula7
